moduextension/__init__.py
moduextension/_version.py
moduextension/labextension/build_log.json
moduextension/labextension/package.json
moduextension/labextension/static/_0275.9190323a55d1088fa6f3.js
moduextension/labextension/static/_0275.9190323a55d1088fa6f3.js.map
moduextension/labextension/static/be3bdb072422fcca72857398ef585f75605538ec7076d2bff66c92b4f73f2dca.png
moduextension/labextension/static/cce90d4aada89def088094db7e8ac2b7096ddcf9cc768e21d143be06ba989b5a.png
moduextension/labextension/static/lib_index_js.0322733605d850f0d524.js
moduextension/labextension/static/lib_index_js.0322733605d850f0d524.js.map
moduextension/labextension/static/lib_index_js.2c0f8f52c9b63b862769.js
moduextension/labextension/static/lib_index_js.2c0f8f52c9b63b862769.js.map
moduextension/labextension/static/lib_index_js.7d731ea6a5c0afcff133.js
moduextension/labextension/static/lib_index_js.7d731ea6a5c0afcff133.js.map
moduextension/labextension/static/lib_index_js.b3140c423d3912c200fa.js
moduextension/labextension/static/lib_index_js.b3140c423d3912c200fa.js.map
moduextension/labextension/static/lib_index_js.da9fab5c9886150beb12.js
moduextension/labextension/static/lib_index_js.da9fab5c9886150beb12.js.map
moduextension/labextension/static/remoteEntry.093e1385bdb2bb9ad36b.js
moduextension/labextension/static/remoteEntry.093e1385bdb2bb9ad36b.js.map
moduextension/labextension/static/remoteEntry.2d1ee6c22e44c60cebbf.js.map
moduextension/labextension/static/remoteEntry.5317625eebc048c1cb5e.js.map
moduextension/labextension/static/remoteEntry.c9d2e62919caa174cc78.js.map
moduextension/labextension/static/remoteEntry.dfce872b8bd935e4f819.js.map
moduextension/labextension/static/style.js
moduextension/labextension/static/style_index_js.330725558f3e80102b0e.js
moduextension/labextension/static/style_index_js.330725558f3e80102b0e.js.map
moduextension/labextension/static/vendors-node_modules_axios_index_js.0ed881817515ee86ea06.js
moduextension-0.1.1.dist-info/LICENSE
moduextension-0.1.1.dist-info/METADATA
moduextension-0.1.1.dist-info/WHEEL
moduextension-0.1.1.dist-info/top_level.txt
moduextension-0.1.1.dist-info/RECORD
